README.rst
pyjf3.py
setup.py
pyjf3.egg-info/PKG-INFO
pyjf3.egg-info/SOURCES.txt
pyjf3.egg-info/dependency_links.txt
pyjf3.egg-info/top_level.txt
test/test_pyjf.py