Metadata-Version: 1.1
Name: pyjf3
Version: 0.2
Summary: Japanese text functions for Python 3
Home-page: https://github.com/atsuoishimoto/pyjf3
Author: Atsuo Ishimoto
Author-email: ishimoto@gembook.org
License: MIT License
Platform: UNKNOWN
Classifier: Intended Audience :: Developers
Classifier: License :: OSI Approved :: MIT License
Classifier: Programming Language :: Python
